[{"morning":{"first":"Isaiah+61","second":"John+1:43-51"},"evening":{"first":"Zechariah+4","second":"Colossians+3:1-18"}},{"morning":{"first":"1+Samuel+26","second":"Luke+22:1-31"},"evening":{"first":"1+Samuel+28:3-25","second":"Colossians+3:18-4:7"}},{"morning":{"first":"1+Samuel+31","second":"Luke+22:31:1-54"},"evening":{"first":"2+Samuel+1","second":"Colossians+4:7-18"}},{"morning":{"first":"2+Samuel+3:17-39","second":"Luke+22:54-71"},"evening":{"first":"2+Samuel+4","second":"1+Thessalonians+1"}},{"morning":{"first":"2+Samuel+6","second":"Luke+23:1-26"},"evening":{"first":"2+Samuel+7:1-18","second":"1+Thessalonians+2"}},{"morning":{"first":"2+Samuel+7:18-29","second":"Luke+23:26-50"},"evening":{"first":"2+Samuel+9","second":"1+Thessalonians+3"}},{"morning":{"first":"2+Samuel+11","second":"Luke+23:50-24:13"},"evening":{"first":"2+Samuel+12:1-24","second":"1+Thessalonians+4"}},{"morning":{"first":"2+Samuel+13:38-14:26","second":"Luke+24:13-53"},"evening":{"first":"2+Samuel+15:1-16","second":"1+Thessalonians+5"}},{"morning":{"first":"2+Samuel+15:16-37","second":"John+1:1-29"},"evening":{"first":"2+Samuel+16:1-15","second":"2+Thessalonians+1"}},{"morning":{"first":"2+Samuel+16:15-17:24","second":"John+1:29-51"},"evening":{"first":"2+Samuel+17:24-18:18","second":"2+Thessalonians+2"}},{"morning":{"first":"2+Samuel+18:18-33","second":"John+2"},"evening":{"first":"2+Samuel+19:1-24","second":"2+Thessalonians+3"}},{"morning":{"first":"2+Samuel+19:24-43","second":"John+3:1-22"},"evening":{"first":"2+Samuel+21:1-15","second":"1+Timothy+1:1-17"}},{"morning":{"first":"2+Samuel+23:1-24","second":"John+3:22-36"},"evening":{"first":"2+Samuel+24","second":"1+Timothy+1:18 & 2"}},{"morning":{"first":"1+Kings+1:1-28","second":"John+4:1-31"},"evening":{"first":"1+Kings+1:28-49","second":"1+Timothy+3"}},{"morning":{"first":"1+Chronicles+29:10-30","second":"John+4:31-54"},"evening":{"first":"1+Kings+3","second":"1+Timothy+4"}},{"morning":{"first":"1+Kings+4:20-34","second":"John+5:1-24"},"evening":{"first":"1+Kings+5","second":"1+Timothy+5"}},{"morning":{"first":"1+Kings+6:1-15","second":"John+5:24-47"},"evening":{"first":"1+Kings+8:1-22","second":"1+Timothy+6"}},{"morning":{"first":"1+Kings+8:22:1-54","second":"John+6:1-22"},"evening":{"first":"1+Kings+8:54-9:10","second":"2+Timothy+1"}},{"morning":{"first":"1+Kings+10","second":"John+6:22-41"},"evening":{"first":"1+Kings+11:1-26","second":"2+Timothy+2"}},{"morning":{"first":"1+Kings+11:26-43","second":"John+6:41-71"},"evening":{"first":"1+Kings+12:1-25","second":"2+Timothy+3"}},{"morning":{"first":"1+Kings+12:25-13:11","second":"John+7:1-25"},"evening":{"first":"1+Kings+13:11-34","second":"2+Timothy+4"}},{"morning":{"first":"1+Kings+14:1-21","second":"John+7:25-53"},"evening":{"first":"1+Kings+15:25-16:8","second":"Titus+1"}},{"morning":{"first":"1+Kings+16:8-34","second":"John+8:1-31"},"evening":{"first":"1+Kings+17","second":"Titus+2"}},{"morning":{"first":"1+Kings+18:1-17","second":"John+8:31-59"},"evening":{"first":"1+Kings+18:17-46","second":"Titus+3"}},{"morning":{"first":"1+Kings+19","second":"John+9:1-39"},"evening":{"first":"1+Kings+21","second":"Philemon"}},{"morning":{"first":"1+Kings+22:1-41","second":"John+9:39-10:22"},"evening":{"first":"2+Kings+1","second":"Hebrews+1"}},{"morning":{"first":"2+Kings+2","second":"John+10:22-42"},"evening":{"first":"2+Kings+4:8-44","second":"Hebrews+2:1-3:7"}},{"morning":{"first":"2+Kings+5","second":"John+11:1-17"},"evening":{"first":"2+Kings+6:1-24","second":"Hebrews+3:7-4:14"}},{"morning":{"first":"2+Kings+6:24-33","second":"John+11:17-47"},"evening":{"first":"2+Kings+7","second":"Hebrews+4:14 & 5"}},{"morning":{"first":"2+Kings+8:1-16","second":"John+11:47-12:20"},"evening":{"first":"2+Kings+9","second":"Hebrews+6"}},{"morning":{"first":"2+Kings+10:1-18","second":"John+12:20-50"},"evening":{"first":"2+Kings+10:18-36","second":"Hebrews+7"}}]